[
  {
    "userId": "user_2P0xrxG8MvcW2DCosLJimclY3Qy",
    "assessmentType": "Anxiety",
    "score": 7,
    "level": "Good",
    "levelDescription": "Good",
    "createdAt": "2023-03-01T12:00:00Z",
    "updatedAt": "2023-03-01T12:00:00Z"
  },
  {
    "userId": "user_2D0xrxG8MvcW2DCosLJimclY3Qy",
    "assessmentType": "burnout",
    "score": 23,
    "level": "Moderate",
    "levelDescription": "Moderate",
    "createdAt": "2023-03-26T12:00:00Z",
    "updatedAt": "2023-03-07T12:00:00Z"
  },
  {
    "userId": "user_2O0xrxG8MvcW2DCosLJimclY3Qy",
    "assessmentType": "burnout",
    "score": 49,
    "level": "Moderate",
    "levelDescription": "Moderate",
    "createdAt": "2023-03-17T12:00:00Z",
    "updatedAt": "2023-03-01T12:00:00Z"
  },
  {
    "userId": "user_2E0xrxG8MvcW2DCosLJimclY3Qy",
    "assessmentType": "depression",
    "score": 9,
    "level": "Moderate",
    "levelDescription": "Moderate",
    "createdAt": "2023-03-28T12:00:00Z",
    "updatedAt": "2023-03-09T12:00:00Z"
  },
  {
    "userId": "user_2I0xrxG8MvcW2DCosLJimclY3Qy",
    "assessmentType": "depression",
    "score": 23,
    "level": "Critical",
    "levelDescription": "Critical",
    "createdAt": "2023-03-24T12:00:00Z",
    "updatedAt": "2023-03-04T12:00:00Z"
  },
  {
    "userId": "user_2W0xrxG8MvcW2DCosLJimclY3Qy",
    "assessmentType": "depression",
    "score": 5,
    "level": "Moderate",
    "levelDescription": "Moderate",
    "createdAt": "2023-03-04T12:00:00Z",
    "updatedAt": "2023-03-25T12:00:00Z"
  },
  {
    "userId": "user_2F0xrxG8MvcW2DCosLJimclY3Qy",
    "assessmentType": "Anxiety",
    "score": 15,
    "level": "Good",
    "levelDescription": "Good",
    "createdAt": "2023-03-25T12:00:00Z",
    "updatedAt": "2023-03-18T12:00:00Z"
  },
  {
    "userId": "user_2L0xrxG8MvcW2DCosLJimclY3Qy",
    "assessmentType": "Anxiety",
    "score": 17,
    "level": "Good",
    "levelDescription": "Good",
    "createdAt": "2023-03-20T12:00:00Z",
    "updatedAt": "2023-03-12T12:00:00Z"
  },
  {
    "userId": "user_2G0xrxG8MvcW2DCosLJimclY3Qy",
    "assessmentType": "depression",
    "score": 19,
    "level": "Critical",
    "levelDescription": "Critical",
    "createdAt": "2023-03-12T12:00:00Z",
    "updatedAt": "2023-03-22T12:00:00Z"
  },
  {
    "userId": "user_2B0xrxG8MvcW2DCosLJimclY3Qy",
    "assessmentType": "burnout",
    "score": 39,
    "level": "Moderate",
    "levelDescription": "Moderate",
    "createdAt": "2023-03-28T12:00:00Z",
    "updatedAt": "2023-03-28T12:00:00Z"
  },
  {
    "userId": "user_2E0xrxG8MvcW2DCosLJimclY3Qy",
    "assessmentType": "burnout",
    "score": 34,
    "level": "Moderate",
    "levelDescription": "Moderate",
    "createdAt": "2023-03-16T12:00:00Z",
    "updatedAt": "2023-03-13T12:00:00Z"
  },
  {
    "userId": "user_2Q0xrxG8MvcW2DCosLJimclY3Qy",
    "assessmentType": "depression",
    "score": 11,
    "level": "Moderate",
    "levelDescription": "Moderate",
    "createdAt": "2023-03-14T12:00:00Z",
    "updatedAt": "2023-03-19T12:00:00Z"
  },
  {
    "userId": "user_2C0xrxG8MvcW2DCosLJimclY3Qy",
    "assessmentType": "burnout",
    "score": 11,
    "level": "Good",
    "levelDescription": "Good",
    "createdAt": "2023-03-09T12:00:00Z",
    "updatedAt": "2023-03-26T12:00:00Z"
  },
  {
    "userId": "user_2A0xrxG8MvcW2DCosLJimclY3Qy",
    "assessmentType": "Anxiety",
    "score": 3,
    "level": "Good",
    "levelDescription": "Good",
    "createdAt": "2023-03-11T12:00:00Z",
    "updatedAt": "2023-03-01T12:00:00Z"
  },
  {
    "userId": "user_2Q0xrxG8MvcW2DCosLJimclY3Qy",
    "assessmentType": "burnout",
    "score": 35,
    "level": "Moderate",
    "levelDescription": "Moderate",
    "createdAt": "2023-04-25T12:00:00Z",
    "updatedAt": "2023-04-27T12:00:00Z"
  },
  {
    "userId": "user_2F0xrxG8MvcW2DCosLJimclY3Qy",
    "assessmentType": "burnout",
    "score": 35,
    "level": "Moderate",
    "levelDescription": "Moderate",
    "createdAt": "2023-04-04T12:00:00Z",
    "updatedAt": "2023-04-04T12:00:00Z"
  },
  {
    "userId": "user_2P0xrxG8MvcW2DCosLJimclY3Qy",
    "assessmentType": "burnout",
    "score": 2,
    "level": "Good",
    "levelDescription": "Good",
    "createdAt": "2023-04-08T12:00:00Z",
    "updatedAt": "2023-04-05T12:00:00Z"
  },
  {
    "userId": "user_2W0xrxG8MvcW2DCosLJimclY3Qy",
    "assessmentType": "Anxiety",
    "score": 15,
    "level": "Good",
    "levelDescription": "Good",
    "createdAt": "2023-04-20T12:00:00Z",
    "updatedAt": "2023-04-28T12:00:00Z"
  },
  {
    "userId": "user_2D0xrxG8MvcW2DCosLJimclY3Qy",
    "assessmentType": "burnout",
    "score": 50,
    "level": "Critical",
    "levelDescription": "Critical",
    "createdAt": "2023-04-17T12:00:00Z",
    "updatedAt": "2023-04-21T12:00:00Z"
  },
  {
    "userId": "user_2E0xrxG8MvcW2DCosLJimclY3Qy",
    "assessmentType": "burnout",
    "score": 17,
    "level": "Good",
    "levelDescription": "Good",
    "createdAt": "2023-04-10T12:00:00Z",
    "updatedAt": "2023-04-05T12:00:00Z"
  },
  {
    "userId": "user_2C0xrxG8MvcW2DCosLJimclY3Qy",
    "assessmentType": "depression",
    "score": 14,
    "level": "Moderate",
    "levelDescription": "Moderate",
    "createdAt": "2023-04-21T12:00:00Z",
    "updatedAt": "2023-04-06T12:00:00Z"
  },
  {
    "userId": "user_2O0xrxG8MvcW2DCosLJimclY3Qy",
    "assessmentType": "burnout",
    "score": 59,
    "level": "Critical",
    "levelDescription": "Critical",
    "createdAt": "2023-04-07T12:00:00Z",
    "updatedAt": "2023-04-27T12:00:00Z"
  },
  {
    "userId": "user_2L0xrxG8MvcW2DCosLJimclY3Qy",
    "assessmentType": "burnout",
    "score": 31,
    "level": "Moderate",
    "levelDescription": "Moderate",
    "createdAt": "2023-04-07T12:00:00Z",
    "updatedAt": "2023-04-01T12:00:00Z"
  },
  {
    "userId": "user_2E0xrxG8MvcW2DCosLJimclY3Qy",
    "assessmentType": "burnout",
    "score": 26,
    "level": "Moderate",
    "levelDescription": "Moderate",
    "createdAt": "2023-04-08T12:00:00Z",
    "updatedAt": "2023-04-14T12:00:00Z"
  },
  {
    "userId": "user_2B0xrxG8MvcW2DCosLJimclY3Qy",
    "assessmentType": "burnout",
    "score": 25,
    "level": "Moderate",
    "levelDescription": "Moderate",
    "createdAt": "2023-04-01T12:00:00Z",
    "updatedAt": "2023-04-04T12:00:00Z"
  },
  {
    "userId": "user_2A0xrxG8MvcW2DCosLJimclY3Qy",
    "assessmentType": "burnout",
    "score": 10,
    "level": "Good",
    "levelDescription": "Good",
    "createdAt": "2023-04-04T12:00:00Z",
    "updatedAt": "2023-04-18T12:00:00Z"
  },
  {
    "userId": "user_2G0xrxG8MvcW2DCosLJimclY3Qy",
    "assessmentType": "Anxiety",
    "score": 13,
    "level": "Good",
    "levelDescription": "Good",
    "createdAt": "2023-04-10T12:00:00Z",
    "updatedAt": "2023-04-24T12:00:00Z"
  },
  {
    "userId": "user_2I0xrxG8MvcW2DCosLJimclY3Qy",
    "assessmentType": "depression",
    "score": 11,
    "level": "Moderate",
    "levelDescription": "Moderate",
    "createdAt": "2023-04-09T12:00:00Z",
    "updatedAt": "2023-04-03T12:00:00Z"
  },
  {
    "userId": "user_2Q0xrxG8MvcW2DCosLJimclY3Qy",
    "assessmentType": "depression",
    "score": 8,
    "level": "Moderate",
    "levelDescription": "Moderate",
    "createdAt": "2023-05-18T12:00:00Z",
    "updatedAt": "2023-05-08T12:00:00Z"
  },
  {
    "userId": "user_2O0xrxG8MvcW2DCosLJimclY3Qy",
    "assessmentType": "burnout",
    "score": 57,
    "level": "Critical",
    "levelDescription": "Critical",
    "createdAt": "2023-05-24T12:00:00Z",
    "updatedAt": "2023-05-06T12:00:00Z"
  },
  {
    "userId": "user_2B0xrxG8MvcW2DCosLJimclY3Qy",
    "assessmentType": "Anxiety",
    "score": 19,
    "level": "Moderate",
    "levelDescription": "Moderate",
    "createdAt": "2023-05-27T12:00:00Z",
    "updatedAt": "2023-05-20T12:00:00Z"
  },
  {
    "userId": "user_2L0xrxG8MvcW2DCosLJimclY3Qy",
    "assessmentType": "burnout",
    "score": 50,
    "level": "Critical",
    "levelDescription": "Critical",
    "createdAt": "2023-05-07T12:00:00Z",
    "updatedAt": "2023-05-25T12:00:00Z"
  },
  {
    "userId": "user_2A0xrxG8MvcW2DCosLJimclY3Qy",
    "assessmentType": "burnout",
    "score": 23,
    "level": "Moderate",
    "levelDescription": "Moderate",
    "createdAt": "2023-05-11T12:00:00Z",
    "updatedAt": "2023-05-06T12:00:00Z"
  },
  {
    "userId": "user_2W0xrxG8MvcW2DCosLJimclY3Qy",
    "assessmentType": "Anxiety",
    "score": 4,
    "level": "Good",
    "levelDescription": "Good",
    "createdAt": "2023-05-16T12:00:00Z",
    "updatedAt": "2023-05-12T12:00:00Z"
  },
  {
    "userId": "user_2I0xrxG8MvcW2DCosLJimclY3Qy",
    "assessmentType": "Anxiety",
    "score": 8,
    "level": "Good",
    "levelDescription": "Good",
    "createdAt": "2023-05-07T12:00:00Z",
    "updatedAt": "2023-05-10T12:00:00Z"
  },
  {
    "userId": "user_2E0xrxG8MvcW2DCosLJimclY3Qy",
    "assessmentType": "burnout",
    "score": 32,
    "level": "Moderate",
    "levelDescription": "Moderate",
    "createdAt": "2023-05-18T12:00:00Z",
    "updatedAt": "2023-05-23T12:00:00Z"
  },
  {
    "userId": "user_2D0xrxG8MvcW2DCosLJimclY3Qy",
    "assessmentType": "burnout",
    "score": 10,
    "level": "Good",
    "levelDescription": "Good",
    "createdAt": "2023-05-26T12:00:00Z",
    "updatedAt": "2023-05-20T12:00:00Z"
  },
  {
    "userId": "user_2G0xrxG8MvcW2DCosLJimclY3Qy",
    "assessmentType": "depression",
    "score": 27,
    "level": "Critical",
    "levelDescription": "Critical",
    "createdAt": "2023-05-14T12:00:00Z",
    "updatedAt": "2023-05-06T12:00:00Z"
  },
  {
    "userId": "user_2F0xrxG8MvcW2DCosLJimclY3Qy",
    "assessmentType": "depression",
    "score": 12,
    "level": "Moderate",
    "levelDescription": "Moderate",
    "createdAt": "2023-05-27T12:00:00Z",
    "updatedAt": "2023-05-23T12:00:00Z"
  },
  {
    "userId": "user_2C0xrxG8MvcW2DCosLJimclY3Qy",
    "assessmentType": "Anxiety",
    "score": 19,
    "level": "Moderate",
    "levelDescription": "Moderate",
    "createdAt": "2023-05-04T12:00:00Z",
    "updatedAt": "2023-05-23T12:00:00Z"
  },
  {
    "userId": "user_2E0xrxG8MvcW2DCosLJimclY3Qy",
    "assessmentType": "depression",
    "score": 20,
    "level": "Critical",
    "levelDescription": "Critical",
    "createdAt": "2023-05-02T12:00:00Z",
    "updatedAt": "2023-05-21T12:00:00Z"
  },
  {
    "userId": "user_2P0xrxG8MvcW2DCosLJimclY3Qy",
    "assessmentType": "Anxiety",
    "score": 13,
    "level": "Good",
    "levelDescription": "Good",
    "createdAt": "2023-05-24T12:00:00Z",
    "updatedAt": "2023-05-28T12:00:00Z"
  },
  {
    "userId": "user_2W0xrxG8MvcW2DCosLJimclY3Qy",
    "assessmentType": "Anxiety",
    "score": 16,
    "level": "Good",
    "levelDescription": "Good",
    "createdAt": "2023-06-19T12:00:00Z",
    "updatedAt": "2023-06-18T12:00:00Z"
  },
  {
    "userId": "user_2P0xrxG8MvcW2DCosLJimclY3Qy",
    "assessmentType": "burnout",
    "score": 57,
    "level": "Critical",
    "levelDescription": "Critical",
    "createdAt": "2023-06-27T12:00:00Z",
    "updatedAt": "2023-06-24T12:00:00Z"
  },
  {
    "userId": "user_2E0xrxG8MvcW2DCosLJimclY3Qy",
    "assessmentType": "burnout",
    "score": 27,
    "level": "Moderate",
    "levelDescription": "Moderate",
    "createdAt": "2023-06-20T12:00:00Z",
    "updatedAt": "2023-06-13T12:00:00Z"
  },
  {
    "userId": "user_2Q0xrxG8MvcW2DCosLJimclY3Qy",
    "assessmentType": "Anxiety",
    "score": 1,
    "level": "Good",
    "levelDescription": "Good",
    "createdAt": "2023-06-18T12:00:00Z",
    "updatedAt": "2023-06-06T12:00:00Z"
  },
  {
    "userId": "user_2A0xrxG8MvcW2DCosLJimclY3Qy",
    "assessmentType": "depression",
    "score": 4,
    "level": "Good",
    "levelDescription": "Good",
    "createdAt": "2023-06-28T12:00:00Z",
    "updatedAt": "2023-06-05T12:00:00Z"
  },
  {
    "userId": "user_2B0xrxG8MvcW2DCosLJimclY3Qy",
    "assessmentType": "depression",
    "score": 26,
    "level": "Critical",
    "levelDescription": "Critical",
    "createdAt": "2023-06-10T12:00:00Z",
    "updatedAt": "2023-06-18T12:00:00Z"
  },
  {
    "userId": "user_2O0xrxG8MvcW2DCosLJimclY3Qy",
    "assessmentType": "depression",
    "score": 21,
    "level": "Critical",
    "levelDescription": "Critical",
    "createdAt": "2023-06-04T12:00:00Z",
    "updatedAt": "2023-06-06T12:00:00Z"
  },
  {
    "userId": "user_2D0xrxG8MvcW2DCosLJimclY3Qy",
    "assessmentType": "burnout",
    "score": 32,
    "level": "Moderate",
    "levelDescription": "Moderate",
    "createdAt": "2023-06-11T12:00:00Z",
    "updatedAt": "2023-06-09T12:00:00Z"
  },
  {
    "userId": "user_2G0xrxG8MvcW2DCosLJimclY3Qy",
    "assessmentType": "depression",
    "score": 20,
    "level": "Critical",
    "levelDescription": "Critical",
    "createdAt": "2023-06-19T12:00:00Z",
    "updatedAt": "2023-06-09T12:00:00Z"
  },
  {
    "userId": "user_2F0xrxG8MvcW2DCosLJimclY3Qy",
    "assessmentType": "depression",
    "score": 17,
    "level": "Critical",
    "levelDescription": "Critical",
    "createdAt": "2023-06-25T12:00:00Z",
    "updatedAt": "2023-06-04T12:00:00Z"
  },
  {
    "userId": "user_2L0xrxG8MvcW2DCosLJimclY3Qy",
    "assessmentType": "depression",
    "score": 9,
    "level": "Moderate",
    "levelDescription": "Moderate",
    "createdAt": "2023-06-01T12:00:00Z",
    "updatedAt": "2023-06-15T12:00:00Z"
  },
  {
    "userId": "user_2I0xrxG8MvcW2DCosLJimclY3Qy",
    "assessmentType": "burnout",
    "score": 5,
    "level": "Good",
    "levelDescription": "Good",
    "createdAt": "2023-06-07T12:00:00Z",
    "updatedAt": "2023-06-04T12:00:00Z"
  },
  {
    "userId": "user_2E0xrxG8MvcW2DCosLJimclY3Qy",
    "assessmentType": "depression",
    "score": 14,
    "level": "Moderate",
    "levelDescription": "Moderate",
    "createdAt": "2023-06-18T12:00:00Z",
    "updatedAt": "2023-06-17T12:00:00Z"
  },
  {
    "userId": "user_2C0xrxG8MvcW2DCosLJimclY3Qy",
    "assessmentType": "Anxiety",
    "score": 10,
    "level": "Good",
    "levelDescription": "Good",
    "createdAt": "2023-06-11T12:00:00Z",
    "updatedAt": "2023-06-05T12:00:00Z"
  },
  {
    "userId": "user_2G0xrxG8MvcW2DCosLJimclY3Qy",
    "assessmentType": "burnout",
    "score": 25,
    "level": "Moderate",
    "levelDescription": "Moderate",
    "createdAt": "2023-07-08T12:00:00Z",
    "updatedAt": "2023-07-16T12:00:00Z"
  },
  {
    "userId": "user_2C0xrxG8MvcW2DCosLJimclY3Qy",
    "assessmentType": "depression",
    "score": 26,
    "level": "Critical",
    "levelDescription": "Critical",
    "createdAt": "2023-07-11T12:00:00Z",
    "updatedAt": "2023-07-11T12:00:00Z"
  },
  {
    "userId": "user_2I0xrxG8MvcW2DCosLJimclY3Qy",
    "assessmentType": "depression",
    "score": 9,
    "level": "Moderate",
    "levelDescription": "Moderate",
    "createdAt": "2023-07-19T12:00:00Z",
    "updatedAt": "2023-07-10T12:00:00Z"
  },
  {
    "userId": "user_2W0xrxG8MvcW2DCosLJimclY3Qy",
    "assessmentType": "Anxiety",
    "score": 15,
    "level": "Good",
    "levelDescription": "Good",
    "createdAt": "2023-07-26T12:00:00Z",
    "updatedAt": "2023-07-19T12:00:00Z"
  },
  {
    "userId": "user_2A0xrxG8MvcW2DCosLJimclY3Qy",
    "assessmentType": "burnout",
    "score": 14,
    "level": "Good",
    "levelDescription": "Good",
    "createdAt": "2023-07-20T12:00:00Z",
    "updatedAt": "2023-07-20T12:00:00Z"
  },
  {
    "userId": "user_2B0xrxG8MvcW2DCosLJimclY3Qy",
    "assessmentType": "burnout",
    "score": 69,
    "level": "Critical",
    "levelDescription": "Critical",
    "createdAt": "2023-07-13T12:00:00Z",
    "updatedAt": "2023-07-23T12:00:00Z"
  },
  {
    "userId": "user_2L0xrxG8MvcW2DCosLJimclY3Qy",
    "assessmentType": "Anxiety",
    "score": 19,
    "level": "Moderate",
    "levelDescription": "Moderate",
    "createdAt": "2023-07-10T12:00:00Z",
    "updatedAt": "2023-07-19T12:00:00Z"
  },
  {
    "userId": "user_2Q0xrxG8MvcW2DCosLJimclY3Qy",
    "assessmentType": "burnout",
    "score": 1,
    "level": "Good",
    "levelDescription": "Good",
    "createdAt": "2023-07-07T12:00:00Z",
    "updatedAt": "2023-07-01T12:00:00Z"
  },
  {
    "userId": "user_2D0xrxG8MvcW2DCosLJimclY3Qy",
    "assessmentType": "Anxiety",
    "score": 18,
    "level": "Good",
    "levelDescription": "Good",
    "createdAt": "2023-07-01T12:00:00Z",
    "updatedAt": "2023-07-25T12:00:00Z"
  },
  {
    "userId": "user_2O0xrxG8MvcW2DCosLJimclY3Qy",
    "assessmentType": "burnout",
    "score": 5,
    "level": "Good",
    "levelDescription": "Good",
    "createdAt": "2023-07-14T12:00:00Z",
    "updatedAt": "2023-07-18T12:00:00Z"
  },
  {
    "userId": "user_2E0xrxG8MvcW2DCosLJimclY3Qy",
    "assessmentType": "depression",
    "score": 17,
    "level": "Critical",
    "levelDescription": "Critical",
    "createdAt": "2023-07-20T12:00:00Z",
    "updatedAt": "2023-07-13T12:00:00Z"
  },
  {
    "userId": "user_2E0xrxG8MvcW2DCosLJimclY3Qy",
    "assessmentType": "burnout",
    "score": 46,
    "level": "Moderate",
    "levelDescription": "Moderate",
    "createdAt": "2023-07-10T12:00:00Z",
    "updatedAt": "2023-07-02T12:00:00Z"
  },
  {
    "userId": "user_2P0xrxG8MvcW2DCosLJimclY3Qy",
    "assessmentType": "Anxiety",
    "score": 2,
    "level": "Good",
    "levelDescription": "Good",
    "createdAt": "2023-07-07T12:00:00Z",
    "updatedAt": "2023-07-18T12:00:00Z"
  },
  {
    "userId": "user_2F0xrxG8MvcW2DCosLJimclY3Qy",
    "assessmentType": "Anxiety",
    "score": 17,
    "level": "Good",
    "levelDescription": "Good",
    "createdAt": "2023-07-13T12:00:00Z",
    "updatedAt": "2023-07-22T12:00:00Z"
  },
  {
    "userId": "user_2A0xrxG8MvcW2DCosLJimclY3Qy",
    "assessmentType": "burnout",
    "score": 15,
    "level": "Good",
    "levelDescription": "Good",
    "createdAt": "2023-08-24T12:00:00Z",
    "updatedAt": "2023-08-18T12:00:00Z"
  },
  {
    "userId": "user_2G0xrxG8MvcW2DCosLJimclY3Qy",
    "assessmentType": "depression",
    "score": 27,
    "level": "Critical",
    "levelDescription": "Critical",
    "createdAt": "2023-08-06T12:00:00Z",
    "updatedAt": "2023-08-21T12:00:00Z"
  },
  {
    "userId": "user_2L0xrxG8MvcW2DCosLJimclY3Qy",
    "assessmentType": "depression",
    "score": 6,
    "level": "Moderate",
    "levelDescription": "Moderate",
    "createdAt": "2023-08-14T12:00:00Z",
    "updatedAt": "2023-08-05T12:00:00Z"
  },
  {
    "userId": "user_2D0xrxG8MvcW2DCosLJimclY3Qy",
    "assessmentType": "depression",
    "score": 0,
    "level": "Good",
    "levelDescription": "Good",
    "createdAt": "2023-08-20T12:00:00Z",
    "updatedAt": "2023-08-19T12:00:00Z"
  },
  {
    "userId": "user_2C0xrxG8MvcW2DCosLJimclY3Qy",
    "assessmentType": "burnout",
    "score": 36,
    "level": "Moderate",
    "levelDescription": "Moderate",
    "createdAt": "2023-08-26T12:00:00Z",
    "updatedAt": "2023-08-07T12:00:00Z"
  },
  {
    "userId": "user_2B0xrxG8MvcW2DCosLJimclY3Qy",
    "assessmentType": "burnout",
    "score": 14,
    "level": "Good",
    "levelDescription": "Good",
    "createdAt": "2023-08-17T12:00:00Z",
    "updatedAt": "2023-08-16T12:00:00Z"
  },
  {
    "userId": "user_2F0xrxG8MvcW2DCosLJimclY3Qy",
    "assessmentType": "Anxiety",
    "score": 12,
    "level": "Good",
    "levelDescription": "Good",
    "createdAt": "2023-08-27T12:00:00Z",
    "updatedAt": "2023-08-20T12:00:00Z"
  },
  {
    "userId": "user_2W0xrxG8MvcW2DCosLJimclY3Qy",
    "assessmentType": "Anxiety",
    "score": 13,
    "level": "Good",
    "levelDescription": "Good",
    "createdAt": "2023-08-27T12:00:00Z",
    "updatedAt": "2023-08-14T12:00:00Z"
  },
  {
    "userId": "user_2Q0xrxG8MvcW2DCosLJimclY3Qy",
    "assessmentType": "Anxiety",
    "score": 0,
    "level": "Good",
    "levelDescription": "Good",
    "createdAt": "2023-08-12T12:00:00Z",
    "updatedAt": "2023-08-04T12:00:00Z"
  },
  {
    "userId": "user_2E0xrxG8MvcW2DCosLJimclY3Qy",
    "assessmentType": "depression",
    "score": 26,
    "level": "Critical",
    "levelDescription": "Critical",
    "createdAt": "2023-08-02T12:00:00Z",
    "updatedAt": "2023-08-23T12:00:00Z"
  },
  {
    "userId": "user_2P0xrxG8MvcW2DCosLJimclY3Qy",
    "assessmentType": "burnout",
    "score": 10,
    "level": "Good",
    "levelDescription": "Good",
    "createdAt": "2023-08-15T12:00:00Z",
    "updatedAt": "2023-08-03T12:00:00Z"
  },
  {
    "userId": "user_2O0xrxG8MvcW2DCosLJimclY3Qy",
    "assessmentType": "Anxiety",
    "score": 15,
    "level": "Good",
    "levelDescription": "Good",
    "createdAt": "2023-08-10T12:00:00Z",
    "updatedAt": "2023-08-21T12:00:00Z"
  },
  {
    "userId": "user_2E0xrxG8MvcW2DCosLJimclY3Qy",
    "assessmentType": "depression",
    "score": 23,
    "level": "Critical",
    "levelDescription": "Critical",
    "createdAt": "2023-08-14T12:00:00Z",
    "updatedAt": "2023-08-11T12:00:00Z"
  },
  {
    "userId": "user_2I0xrxG8MvcW2DCosLJimclY3Qy",
    "assessmentType": "burnout",
    "score": 62,
    "level": "Critical",
    "levelDescription": "Critical",
    "createdAt": "2023-08-09T12:00:00Z",
    "updatedAt": "2023-08-20T12:00:00Z"
  },
  {
    "userId": "user_2B0xrxG8MvcW2DCosLJimclY3Qy",
    "assessmentType": "depression",
    "score": 0,
    "level": "Good",
    "levelDescription": "Good",
    "createdAt": "2023-09-16T12:00:00Z",
    "updatedAt": "2023-09-20T12:00:00Z"
  },
  {
    "userId": "user_2G0xrxG8MvcW2DCosLJimclY3Qy",
    "assessmentType": "burnout",
    "score": 27,
    "level": "Moderate",
    "levelDescription": "Moderate",
    "createdAt": "2023-09-06T12:00:00Z",
    "updatedAt": "2023-09-17T12:00:00Z"
  },
  {
    "userId": "user_2O0xrxG8MvcW2DCosLJimclY3Qy",
    "assessmentType": "Anxiety",
    "score": 9,
    "level": "Good",
    "levelDescription": "Good",
    "createdAt": "2023-09-21T12:00:00Z",
    "updatedAt": "2023-09-08T12:00:00Z"
  },
  {
    "userId": "user_2C0xrxG8MvcW2DCosLJimclY3Qy",
    "assessmentType": "depression",
    "score": 17,
    "level": "Critical",
    "levelDescription": "Critical",
    "createdAt": "2023-09-17T12:00:00Z",
    "updatedAt": "2023-09-27T12:00:00Z"
  },
  {
    "userId": "user_2P0xrxG8MvcW2DCosLJimclY3Qy",
    "assessmentType": "burnout",
    "score": 46,
    "level": "Moderate",
    "levelDescription": "Moderate",
    "createdAt": "2023-09-22T12:00:00Z",
    "updatedAt": "2023-09-06T12:00:00Z"
  },
  {
    "userId": "user_2Q0xrxG8MvcW2DCosLJimclY3Qy",
    "assessmentType": "burnout",
    "score": 18,
    "level": "Good",
    "levelDescription": "Good",
    "createdAt": "2023-09-27T12:00:00Z",
    "updatedAt": "2023-09-02T12:00:00Z"
  },
  {
    "userId": "user_2W0xrxG8MvcW2DCosLJimclY3Qy",
    "assessmentType": "depression",
    "score": 19,
    "level": "Critical",
    "levelDescription": "Critical",
    "createdAt": "2023-09-16T12:00:00Z",
    "updatedAt": "2023-09-12T12:00:00Z"
  },
  {
    "userId": "user_2A0xrxG8MvcW2DCosLJimclY3Qy",
    "assessmentType": "depression",
    "score": 1,
    "level": "Good",
    "levelDescription": "Good",
    "createdAt": "2023-09-27T12:00:00Z",
    "updatedAt": "2023-09-03T12:00:00Z"
  },
  {
    "userId": "user_2I0xrxG8MvcW2DCosLJimclY3Qy",
    "assessmentType": "Anxiety",
    "score": 0,
    "level": "Good",
    "levelDescription": "Good",
    "createdAt": "2023-09-12T12:00:00Z",
    "updatedAt": "2023-09-23T12:00:00Z"
  },
  {
    "userId": "user_2E0xrxG8MvcW2DCosLJimclY3Qy",
    "assessmentType": "Anxiety",
    "score": 4,
    "level": "Good",
    "levelDescription": "Good",
    "createdAt": "2023-09-17T12:00:00Z",
    "updatedAt": "2023-09-09T12:00:00Z"
  },
  {
    "userId": "user_2D0xrxG8MvcW2DCosLJimclY3Qy",
    "assessmentType": "Anxiety",
    "score": 1,
    "level": "Good",
    "levelDescription": "Good",
    "createdAt": "2023-09-05T12:00:00Z",
    "updatedAt": "2023-09-26T12:00:00Z"
  },
  {
    "userId": "user_2L0xrxG8MvcW2DCosLJimclY3Qy",
    "assessmentType": "depression",
    "score": 0,
    "level": "Good",
    "levelDescription": "Good",
    "createdAt": "2023-09-19T12:00:00Z",
    "updatedAt": "2023-09-25T12:00:00Z"
  },
  {
    "userId": "user_2F0xrxG8MvcW2DCosLJimclY3Qy",
    "assessmentType": "burnout",
    "score": 4,
    "level": "Good",
    "levelDescription": "Good",
    "createdAt": "2023-09-24T12:00:00Z",
    "updatedAt": "2023-09-16T12:00:00Z"
  },
  {
    "userId": "user_2E0xrxG8MvcW2DCosLJimclY3Qy",
    "assessmentType": "burnout",
    "score": 17,
    "level": "Good",
    "levelDescription": "Good",
    "createdAt": "2023-09-24T12:00:00Z",
    "updatedAt": "2023-09-24T12:00:00Z"
  }
]